{
  "resource": "领导 打分表 查看修改",
  "http_method": "PUT",
  "route": "/leaders/evaluations/:id",
  "description": "领导 打分表 修改成功",
  "explanation": null,
  "parameters": [
    {
      "require": false,
      "scope": "evaluation",
      "name": "thought_morals",
      "description": "思想道德情况"
    },
    {
      "require": false,
      "scope": "evaluation",
      "name": "duties",
      "description": "履行岗位职责情况"
    },
    {
      "require": false,
      "scope": "evaluation",
      "name": "upright_incorruptiable",
      "description": "廉洁自律情况"
    },
    {
      "require": false,
      "scope": "evaluation",
      "name": "evaluation_totality",
      "description": "总体评价"
    }
  ],
  "response_fields": [

  ],
  "requests": [
    {
      "request_method": "PUT",
      "request_path": "/leaders/evaluations/1",
      "request_body": "evaluation[thought_morals]=new+thought_morals&evaluation[duties]=new+upright_incorruptiable&evaluation[upright_incorruptiable]=new+duties&evaluation[evaluation_totality]=100",
      "request_headers": {
        "Accept": "application/json",
        "X-Leader-Token": "l_qwertyuiop1",
        "X-Leader-Job-Num": "leader_job_num",
        "X-Leader-Email": "l_hahaha@haha.com",
        "Host": "example.org",
        "Content-Type": "application/x-www-form-urlencoded",
        "Cookie": ""
      },
      "request_query_parameters": {
      },
      "request_content_type": "application/x-www-form-urlencoded",
      "response_status": 201,
      "response_status_text": "Created",
      "response_body": "{\n  \"id\": 1,\n  \"thought_morals\": \"new thought_morals\",\n  \"upright_incorruptiable\": \"new duties\",\n  \"duties\": \"new upright_incorruptiable\",\n  \"evaluation_totality\": 100,\n  \"self_evaluation_id\": 1,\n  \"user_id\": 1,\n  \"user_type\": \"leader\"\n}",
      "response_headers": {
        "X-Frame-Options": "SAMEORIGIN",
        "X-XSS-Protection": "1; mode=block",
        "X-Content-Type-Options": "nosniff",
        "Content-Type": "application/json; charset=utf-8",
        "ETag": "W/\"9813c0f71d494be8d91a5ba9e3e6e5b7\"",
        "Cache-Control": "max-age=0, private, must-revalidate",
        "X-Request-Id": "dc9471bb-f5f3-42df-bbb2-f9f22e6c19c7",
        "X-Runtime": "0.017830",
        "Vary": "Origin",
        "Content-Length": "204"
      },
      "response_content_type": "application/json; charset=utf-8",
      "curl": null
    }
  ]
}